qcompute_qapp/__init__.py
qcompute_qapp/algorithm/__init__.py
qcompute_qapp/algorithm/kernel_classifier.py
qcompute_qapp/algorithm/qaoa.py
qcompute_qapp/algorithm/ssvqe.py
qcompute_qapp/algorithm/vqe.py
qcompute_qapp/application/__init__.py
qcompute_qapp/application/chemistry/__init__.py
qcompute_qapp/application/chemistry/molecular_ground_state_energy.py
qcompute_qapp/application/optimization/__init__.py
qcompute_qapp/application/optimization/max_cut.py
qcompute_qapp/circuit/__init__.py
qcompute_qapp/circuit/basic_circuit.py
qcompute_qapp/circuit/encoding_circuit.py
qcompute_qapp/circuit/kernel_estimation_circuit.py
qcompute_qapp/circuit/parameterized_circuit.py
qcompute_qapp/circuit/parameterized_circuit_template.py
qcompute_qapp/circuit/pauli_measurement_circuit.py
qcompute_qapp/circuit/qaoa_ansatz.py
qcompute_qapp/optimizer/__init__.py
qcompute_qapp/optimizer/basic_optimizer.py
qcompute_qapp/optimizer/powell.py
qcompute_qapp/optimizer/sgd.py
qcompute_qapp/optimizer/slsqp.py
qcompute_qapp/optimizer/smo.py
qcompute_qapp/optimizer/spsa.py
qcompute_qapp/utils/__init__.py
qcompute_qapp/utils/hamiltonian_cliques.py
qcompute_qapp/utils/hamiltonian_matrix.py
qcompute_qapp-0.0.1.dist-info/METADATA
qcompute_qapp-0.0.1.dist-info/WHEEL
qcompute_qapp-0.0.1.dist-info/top_level.txt
qcompute_qapp-0.0.1.dist-info/RECORD
