Metadata-Version: 2.1
Name: qcompute-qapp
Version: 0.0.1
Summary: A quantum computing toolbox based on the QCompute component of Quantum Leaf which provides quantum computing services for solving practical problems.
Home-page: https://quantum-hub.baidu.com/qapp/
Author: Institute for Quantum Computing, Baidu INC.
Author-email: quantum@baidu.com
Project-URL: Documentation, https://quantum-hub.baidu.com/qapp/tutorial-overview
Project-URL: Source, https://github.com/baidu/QCompute/tree/master/Extensions/QuantumApplication
Project-URL: Tracker, https://github.com/PaddlePaddle/Quantum/issues
Classifier: Programming Language :: Python :: 3
Classifier: License :: OSI Approved :: Apache Software License
Classifier: Operating System :: OS Independent
Requires-Python: >=3.6, <4
Requires-Dist: networkx (>=2.5.1)
Requires-Dist: numpy (>=1.20.3)
Requires-Dist: tqdm (>=4.58.0)
Requires-Dist: scipy (>=1.6.3)
Requires-Dist: noisyopt (>=0.2.2)
Requires-Dist: qcompute (>=2.0.0)
Requires-Dist: scikit-learn (>=0.24.2)
Requires-Dist: scikit-image
